{"item":{"name":"All Knowledge Articles","tags":{"processCatalogL1":"CS.00 Customer Service Management","processCatalogL2":"CS.10","processCatalogL3":"CS.10.02"},"entity":"knowledgearticle","viewId":"vw-knowledgearticle-all","solution":"ContosoCustomerService","_viewDetails":{"queryType":"SavedQuery","isDefault":false,"isQuickFind":false,"columnCount":6,"filterCount":0,"linkedEntityCount":0,"columns":[{"name":"title","width":200},{"name":"articlepublicnumber","width":150},{"name":"keywords","width":120},{"name":"content","width":100},{"name":"majorversionnumber","width":200},{"name":"statecode","width":150}],"filters":[],"linkedEntities":[],"sortFields":[{"attribute":"con_reviewduedate","descending":true}]}},"metadata":{"type":"views","id":"vw-knowledgearticle-all"}}