{"item":{"name":"All Publishers","tags":{"processCatalogL1":"99.00 Administer to operate","processCatalogL2":"99.01 Implement solutions","processCatalogL3":"99.01.310 Implement application lifecycle management (ALM) strategies"},"entity":"publisher","viewId":"vw-publisher-all","solution":"CenterofExcellenceCoreComponents","_viewDetails":{"queryType":"SavedQuery","isDefault":false,"isQuickFind":false,"columnCount":5,"filterCount":0,"linkedEntityCount":0,"columns":[{"name":"uniquename","width":200},{"name":"friendlyname","width":150},{"name":"customizationprefix","width":120},{"name":"customizationoptionvalueprefix","width":100},{"name":"description","width":200}],"filters":[],"linkedEntities":[],"sortFields":[{"field":"uniquename","descending":true}]}},"metadata":{"type":"views","id":"vw-publisher-all"}}