{"item":{"name":"All Plug-in Types","tags":{"processCatalogL1":"PL.00 Platform & Governance","processCatalogL2":"PL.04","processCatalogL3":""},"entity":"plugintype","viewId":"vw-plugintype-all","solution":"CenterofExcellenceCoreComponents","_viewDetails":{"queryType":"SavedQuery","isDefault":false,"isQuickFind":false,"columnCount":5,"filterCount":0,"linkedEntityCount":0,"columns":[{"name":"typename","width":200},{"name":"friendlyname","width":150},{"name":"assemblyname","width":120},{"name":"isworkflowactivity","width":100},{"name":"version","width":200}],"filters":[],"linkedEntities":[],"sortFields":[{"field":"typename","descending":true}]}},"metadata":{"type":"views","id":"vw-plugintype-all"}}