{"item":{"name":"Active Users","tags":{"processCatalogL1":"PL.00 Platform & Governance","processCatalogL2":"PL.01","processCatalogL3":"PL.01.02"},"entity":"systemuser","viewId":"vw-systemuser-active","solution":"ContosoPlatformGovernance","_viewDetails":{"queryType":"SavedQuery","isDefault":true,"isQuickFind":false,"columnCount":6,"filterCount":1,"linkedEntityCount":0,"columns":[{"name":"fullname","width":200},{"name":"internalemailaddress","width":150},{"name":"azureactivedirectoryobjectid","width":120},{"name":"businessunitid","width":100},{"name":"isdisabled","width":200},{"name":"con_makerpersona","width":150}],"filters":[{"value":"0","operator":"eq","attribute":"statecode"}],"linkedEntities":[],"sortFields":[{"attribute":"con_lastcoeattestation","descending":true}]}},"metadata":{"type":"views","id":"vw-systemuser-active"}}