{"code":"55.50.010","tagField":"processCatalogL3","total":5,"components":[{"name":"Leave Enrollment","type":"Entity","id":"mshr_leaveenrollment","solution":"msdynhr_HumanResources","tags":{"layer":"oob","vertical":"Human Resources / Workforce Management","d365Module":"Human Resources","processCatalogL1":"55.00 Hire to retire","processCatalogL2":"55.50 Manage time and attendance","processCatalogL3":"55.50.010 Develop leave and absence policies"}},{"name":"Leave Enrollment","type":"Form","id":"frm-mshr-leaveenrollment-main","solution":"msdynhr_HumanResources","tags":{"processCatalogL1":"55.00 Hire to retire","processCatalogL2":"55.50 Manage time and attendance","processCatalogL3":"55.50.010 Develop leave and absence policies"}},{"name":"LeaveBalanceValidationPlugin","type":"Plugin","id":"plg-leavebalancevalidationplugin","solution":"ContosoHumanResources","tags":{"processCatalogL1":"55.00 Hire to retire","processCatalogL2":"55.50 Manage time and attendance","processCatalogL3":"55.50.010 Develop leave and absence policies"}},{"name":"Active Leave Enrollments","type":"View","id":"vw-mshr-leaveenrollment-active","solution":"msdynhr_HumanResources","tags":{"processCatalogL1":"55.00 Hire to retire","processCatalogL2":"55.50 Manage time and attendance","processCatalogL3":"55.50.010 Develop leave and absence policies"}},{"name":"All Leave Enrollments","type":"View","id":"vw-mshr-leaveenrollment-all","solution":"msdynhr_HumanResources","tags":{"processCatalogL1":"55.00 Hire to retire","processCatalogL2":"55.50 Manage time and attendance","processCatalogL3":"55.50.010 Develop leave and absence policies"}}]}