{"code":"85.35.400","tagField":"processCatalogL3","total":4,"components":[{"name":"Goal","type":"Entity","id":"goal","solution":"msdyn_SalesPro","tags":{"layer":"oob","vertical":"Cross-industry (B2B enterprise sales)","d365Module":"Sales","processCatalogL1":"85.00 Prospect to quote","processCatalogL2":"85.35 Define sales strategy and policies","processCatalogL3":"85.35.400 Determine sales targets"}},{"name":"Goal","type":"Form","id":"frm-goal-main","solution":"msdyn_SalesPro","tags":{"processCatalogL1":"85.00 Prospect to quote","processCatalogL2":"85.35 Define sales strategy and policies","processCatalogL3":"85.35.400 Determine sales targets"}},{"name":"Active Goals","type":"View","id":"vw-goal-active","solution":"msdyn_SalesPro","tags":{"processCatalogL1":"85.00 Prospect to quote","processCatalogL2":"85.35 Define sales strategy and policies","processCatalogL3":"85.35.400 Determine sales targets"}},{"name":"All Goals","type":"View","id":"vw-goal-all","solution":"msdyn_SalesPro","tags":{"processCatalogL1":"85.00 Prospect to quote","processCatalogL2":"85.35 Define sales strategy and policies","processCatalogL3":"85.35.400 Determine sales targets"}}]}