{"code":"99.20.130","tagField":"processCatalogL3","total":4,"components":[{"name":"Business Unit","type":"Entity","id":"businessunit","solution":"CenterofExcellenceCoreComponents","tags":{"layer":"oob","vertical":"Cross-cutting Platform / Center of Excellence","d365Module":"Platform & Governance (shared core)","processCatalogL1":"99.00 Administer to operate","processCatalogL2":"99.20 Administer system features","processCatalogL3":"99.20.130 Manage organizational structure"}},{"name":"Business Unit","type":"Form","id":"frm-businessunit-main","solution":"CenterofExcellenceCoreComponents","tags":{"processCatalogL1":"99.00 Administer to operate","processCatalogL2":"99.20 Administer system features","processCatalogL3":"99.20.130 Manage organizational structure"}},{"name":"Active Business Units","type":"View","id":"vw-businessunit-active","solution":"CenterofExcellenceCoreComponents","tags":{"processCatalogL1":"99.00 Administer to operate","processCatalogL2":"99.20 Administer system features","processCatalogL3":"99.20.130 Manage organizational structure"}},{"name":"All Business Units","type":"View","id":"vw-businessunit-all","solution":"CenterofExcellenceCoreComponents","tags":{"processCatalogL1":"99.00 Administer to operate","processCatalogL2":"99.20 Administer system features","processCatalogL3":"99.20.130 Manage organizational structure"}}]}