{"item":{"name":"con_/scripts/con-vendor.js","tags":{},"solution":"ContosoSupplyChain","description":"Client-side logic on the Vendor form.","displayName":"Vendor Form Scripts","_codeLineCount":394,"_codeFunctionCount":4,"_codeFunctions":["onLoad","onSave"],"_codeApiCalls":[{"entity":"msdyn_timeentry","operation":"retrieveMultipleRecords"}],"_codeDeprecatedCount":4,"_codeDeprecated":[{"count":4,"pattern":"Xrm.Page"}],"_codeFieldRefs":["name","statuscode","ownerid"],"_codeGovernanceFlags":["Deprecated Xrm.Page API"],"_isRulesEngine":false},"metadata":{"type":"webresources","id":"con_/scripts/con-vendor.js"}}