{"item":{"id":"plg-con-governance-environmentinventoryauditplugin","name":"Con.Governance.EnvironmentInventoryAuditPlugin","tags":{"processCatalogL1":"60.00 Inventory to deliver","processCatalogL2":"60.20 Maintain inventory levels","processCatalogL3":"60.20.040 Count inventory"},"solution":"ContosoPlatformGovernance","businessLogic":"Post-Operation plug-in that writes an immutable audit annotation and enforces uniqueness of con_environmentid whenever an environment inventory record is created or modified."},"metadata":{"type":"plugins","id":"plg-con-governance-environmentinventoryauditplugin"}}