{"item":{"name":"Onboarding Task","tags":{"processCatalogL1":"55.00 Hire to retire","processCatalogL2":"55.10 Recruit and onboard talent","processCatalogL3":"55.10.070 Onboard new employees"},"entity":"con_onboardingtask","formId":"frm-con-onboardingtask-main","formType":"Main","solution":"ContosoHumanResources","_tabCount":1,"_totalFields":8,"_jsHandlerCount":2,"_subgridCount":0,"_tabs":[{"name":"tab_general","label":"General","sections":[{"name":"general","label":"General","columns":[{"label":"Onboarding Task","logicalName":"con_onboardingtaskid"},{"label":"Task Name","logicalName":"con_name"},{"label":"Worker","logicalName":"con_worker"},{"label":"Assigned To","logicalName":"con_assignedto"}],"columnCount":4},{"name":"details","label":"Additional Details","columns":[{"label":"Due Date","logicalName":"con_duedate"},{"label":"Category","logicalName":"con_category"},{"label":"Completed","logicalName":"con_iscompleted"},{"label":"Status Reason","logicalName":"statuscode"}],"columnCount":4}],"fieldCount":8}],"_jsHandlers":[{"event":"onload","control":"form","library":"con_/scripts/con-onboardingtask.js","functionName":"Contoso.conOnboardingtask.onLoad"},{"event":"onchange","control":"con_category","library":"con_/scripts/con-onboardingtask.js","functionName":"Contoso.conOnboardingtask.onStatusChange"}]},"metadata":{"type":"forms","id":"frm-con-onboardingtask-main"}}