{"item":{"name":"Queue Item","tags":{"processCatalogL1":"20.00 Case to resolution","processCatalogL2":"20.40 Manage and work on cases","processCatalogL3":"20.40.070 Track additional information against a case"},"entity":"queueitem","formId":"frm-queueitem-main","formType":"Main","solution":"msdyn_CustomerService","_tabCount":1,"_totalFields":5,"_jsHandlerCount":0,"_subgridCount":0,"_tabs":[{"name":"tab_general","label":"General","sections":[{"name":"general","label":"General","columns":[{"label":"Queue","logicalName":"queueid"},{"label":"Object Type","logicalName":"objecttypecode"},{"label":"Worked By","logicalName":"workerid"}],"columnCount":3},{"name":"details","label":"Additional Details","columns":[{"label":"Entered On","logicalName":"enteredon"},{"label":"Status","logicalName":"statecode"}],"columnCount":2}],"fieldCount":5}],"_jsHandlers":[]},"metadata":{"type":"forms","id":"frm-queueitem-main"}}