{"item":{"name":"Vendor (Quick Create)","tags":{"processCatalogL1":"75.00 Source to pay","processCatalogL2":"75.30 Manage supplier relationships","processCatalogL3":"75.30.030 Manage active suppliers"},"entity":"con_vendor","formId":"frm-con-vendor-qc","formType":"QuickCreate","solution":"ContosoSupplyChain","_tabCount":1,"_totalFields":9,"_jsHandlerCount":2,"_subgridCount":0,"_tabs":[{"name":"tab_general","label":"General","sections":[{"name":"general","label":"General","columns":[{"label":"Vendor","logicalName":"con_vendorid"},{"label":"Vendor Name","logicalName":"con_name"},{"label":"Vendor Account","logicalName":"con_vendoraccount"},{"label":"Account","logicalName":"con_accountid"},{"label":"Vendor Group","logicalName":"con_vendorgroup"}],"columnCount":5},{"name":"details","label":"Additional Details","columns":[{"label":"Approval Status","logicalName":"con_approvalstatus"},{"label":"On-Time Delivery %","logicalName":"con_ontimedeliveryrate"},{"label":"Owner","logicalName":"ownerid"},{"label":"Status","logicalName":"statecode"}],"columnCount":4}],"fieldCount":9}],"_jsHandlers":[{"event":"onload","control":"form","library":"con_/scripts/con-vendor.js","functionName":"Contoso.conVendor.onLoad"},{"event":"onchange","control":"con_vendorgroup","library":"con_/scripts/con-vendor.js","functionName":"Contoso.conVendor.onStatusChange"}]},"metadata":{"type":"forms","id":"frm-con-vendor-qc"}}