{"item":{"id":"wf-24-expense-receipt-required","name":"Expense Receipt Required Rule","tags":{"processCatalogL1":"PJ.00 Project Operations","processCatalogL2":"PJ.01"},"category":"businessrule","solution":"ContosoProjectOperations","description":"Business rule making the receipt attachment mandatory and locking submission when msdyn_amount exceeds the policy threshold until con_receiptverified is true.","primaryEntity":"msdyn_expense","_relEnvVars":["con_projectopsToFinopsDualwriteUrl"],"_complexity":"Medium","_complexityScore":51,"_totalActions":17,"_maxDepth":3,"_hasErrorHandling":true,"_metrics":{"ifCount":2,"httpCount":2,"waitCount":0,"childFlows":0,"scopeCount":1,"switchCount":0,"composeCount":2,"foreachCount":1,"variableCount":1,"terminateCount":0,"connectorActions":1},"_httpUrls":["https://api.contoso.com/projectOperations/v1"],"_relFlowEntities":[{"entity":"msdyn_expense","operations":["Create","Update"]},{"entity":"msdyn_project","operations":["Read"]},{"entity":"bookableresource","operations":["Read"]}]},"metadata":{"type":"workflows","id":"wf-24-expense-receipt-required"}}