{"byL1":{"FS.00 Field Service":66,"HR.00 Human Resources":70,"PJ.00 Project Operations":59,"MK.00 Marketing":62,"FI.00 Finance":63,"PL.00 Platform & Governance":68,"SA.00 Sales":69,"SC.00 Supply Chain Management":59,"CS.00 Customer Service Management":66,"CC.00 Contact Center / Omnichannel Engagement":51,"CI.00 Customer Data Platform (Unified Customer Data)":60,"CO.00 Commerce & Omnichannel Retail":68},"byL2":{"FS.01":25,"HR.02":32,"PJ.04":21,"MK.02":36,"FI.04":20,"FS.04":14,"FS.03":5,"PL.03":10,"SA.01":16,"PL.04":21,"PL.01":13,"SC.20":20,"MK.04":23,"PJ.02":32,"CS.20":26,"CC.20":21,"CI.01":18,"SC.40":19,"SA.02":26,"SA.04":15,"PL.02":24,"HR.03":10,"FI.02":29,"CS.10":18,"CS.30":9,"CI.04":17,"SA.03":12,"CI.02":21,"CC.40":17,"HR.04":14,"CS.40":13,"CO.01":7,"SC.30":9,"FI.03":12,"PJ.03":4,"CC.30":11,"FS.02":22,"SC.50":6,"HR.05":4,"CI.03":4,"CO.02":26,"CO.04":25,"SC.10":5,"CO.03":10,"HR.01":10,"MK.03":1,"MK.01":2,"PJ.01":2,"FI.01":2,"CC.10":2},"byL3":{"FS.01.01":15,"PJ.04.01":8,"FS.01.02":8,"MK.02.01":10,"FI.04.01":8,"FS.03.01":3,"PL.03.01":8,"SA.01.02":6,"PL.01.02":8,"SC.22":8,"PJ.02.02":6,"CS.20.01":8,"HR.02.01":10,"PJ.02.01":8,"CC.22":8,"CI.01.01":10,"PL.04.01":6,"SC.41":10,"CI.01.02":6,"SA.02.01":8,"HR.03.01":6,"CS.10.02":8,"CS.30.01":8,"SC.21":5,"CI.04.01":3,"MK.04.01":8,"SA.03.01":6,"PL.02.01":8,"SA.01.01":8,"HR.04.01":5,"CC.41":3,"PL.01.01":3,"CI.02.01":5,"CO.01.01":5,"HR.02.02":10,"FI.03.01":11,"PJ.03.01":3,"SC.31":3,"CC.31":10,"FS.02.01":8,"SA.03.02":5,"CC.21":5,"CS.10.01":8,"FI.02.01":11,"MK.04.02":3,"CI.03.01":3,"CO.02.01":8,"CO.04.01":8,"MK.02.02":8,"CO.03.01":8},"totalTagged":761}