{"total":20,"byType":{"WebResource":2,"App":7,"SecurityRole":11},"items":[{"name":"con_/html/welcome.html","type":"WebResource","id":"con_/html/welcome.html","solution":"ContosoCore"},{"name":"con_/images/logo.png","type":"WebResource","id":"con_/images/logo.png","solution":"ContosoCore"},{"name":"Contoso Delivery PMO","type":"App","id":"con_contosoDeliveryPmo","solution":"ContosoProjectOperations"},{"name":"Contoso CoE Command Center","type":"App","id":"con_contosoCoeCommandCenter","solution":"ContosoPlatformGovernance"},{"name":"Contoso Time & Expense Capture","type":"App","id":"con_contosoTimeExpenseCapture","solution":"ContosoProjectOperations"},{"name":"Capex Request Intake","type":"App","id":"con_capexRequestIntake","solution":"ContosoFinance"},{"name":"Contoso Curbside Concierge","type":"App","id":"con_contosoCurbsideConcierge","solution":"ContosoCommerce"},{"name":"Contoso Supervisor Coaching","type":"App","id":"con_contosoSupervisorCoaching","solution":"ContosoContactCenter"},{"name":"Maker Attestation (Canvas)","type":"App","id":"con_makerAttestation","solution":"ContosoPlatformGovernance"},{"name":"con_Resourcing Desk Coordinator","type":"SecurityRole","id":"role-con-resourcing-desk-coordinator","solution":"ContosoProjectOperations"},{"name":"CI Data Contributor","type":"SecurityRole","id":"role-ci-data-contributor","solution":"msdynci_CustomerInsights"},{"name":"Contoso Segment Activator","type":"SecurityRole","id":"role-contoso-segment-activator","solution":"ContosoCustomerInsights"},{"name":"Financial Controller","type":"SecurityRole","id":"role-financial-controller","solution":"ContosoFinance"},{"name":"Store Associate (POS)","type":"SecurityRole","id":"role-store-associate-pos","solution":"ContosoCommerce"},{"name":"Contoso HR Business Partner","type":"SecurityRole","id":"role-contoso-hr-business-partner","solution":"ContosoHumanResources"},{"name":"Contoso Employee Relations Specialist","type":"SecurityRole","id":"role-contoso-employee-relations-specialist","solution":"ContosoHumanResources"},{"name":"Omnichannel agent","type":"SecurityRole","id":"role-omnichannel-agent","solution":"msdyn_OmnichannelBase"},{"name":"Omnichannel supervisor","type":"SecurityRole","id":"role-omnichannel-supervisor","solution":"msdyn_OmnichannelBase"},{"name":"Contoso CC Quality Analyst","type":"SecurityRole","id":"role-contoso-cc-quality-analyst","solution":"ContosoContactCenter"},{"name":"Con - CoE Data Protection Officer","type":"SecurityRole","id":"role-con-coe-data-protection-officer","solution":"ContosoPlatformGovernance"}]}