{"item":{"tags":{"layer":"oob","vertical":"Professional Services / Project-Based Business","d365Module":"Project Operations","processCatalogL1":"95.00 Service to deliver","processCatalogL2":"95.25 Manage service work","processCatalogL3":"95.25.400 Deploy service resources"},"solution":"msdyn_ProjectServiceCore","_category":"projectOperations","description":"Assignment linking a project team member to a project task with an effort distribution across the task date range.","displayName":"Resource Assignment","logicalName":"msdyn_resourceassignment","_relFormCount":1,"_relFormDetails":[{"name":"Resource Assignment","entity":"msdyn_resourceassignment","formType":"Main","formId":"frm-msdyn-resourceassignment-main"}],"_relViewCount":2,"_relViewDetails":[{"name":"Active Resource Assignments","entity":"msdyn_resourceassignment","viewId":"vw-msdyn-resourceassignment-active"},{"name":"All Resource Assignments","entity":"msdyn_resourceassignment","viewId":"vw-msdyn-resourceassignment-all"}],"_relOptionSetCount":1,"_relPluginStepCount":0,"_relPluginStepDetails":[],"_relApps":[],"_colTotal":null,"_colCustom":null,"_colOOB":null,"_columns":[{"type":"string","displayName":"Name","logicalName":"msdyn_name"},{"type":"decimal","displayName":"Effort","logicalName":"msdyn_effort"},{"type":"datetime","displayName":"From","logicalName":"msdyn_from"},{"type":"datetime","displayName":"To","logicalName":"msdyn_to"},{"type":"optionset","displayName":"Status","logicalName":"statecode"}],"_entitySettings":null,"_relEntityRels":[{"name":"msdyn_projecttask_msdyn_resourceassignment","type":"OneToMany","fromEntity":"msdyn_projecttask","toEntity":"msdyn_resourceassignment","lookupField":"msdyn_taskid","cascadeDelete":"Cascade"},{"name":"msdyn_projectteam_msdyn_resourceassignment","type":"OneToMany","fromEntity":"msdyn_projectteam","toEntity":"msdyn_resourceassignment","lookupField":"msdyn_projectteamid","cascadeDelete":"Cascade"},{"name":"msdyn_project_msdyn_resourceassignment","type":"OneToMany","fromEntity":"msdyn_project","toEntity":"msdyn_resourceassignment","lookupField":"msdyn_projectid","cascadeDelete":"Cascade"}],"_relSolutionFootprint":["msdyn_ProjectServiceCore"]},"metadata":{"type":"entities","id":"msdyn_resourceassignment"}}