{"item":{"tags":{"layer":"virtual","vertical":"Manufacturing & Distribution","d365Module":"Supply Chain Management","processCatalogL1":"SC.00 Supply Chain Management","processCatalogL2":"SC.30","processCatalogL3":"SC.31"},"solution":"msdyn_SupplyChain","_category":"supplyChainManagement","description":"F&O PurchaseOrderLinesV2 surfaced via dual-write (msdyn_purchaseorderline). PurchLine equivalent; line-level item, quantity, and receiving-warehouse detail.","displayName":"Purchase Order Line","logicalName":"msdyn_purchaseorderline","_relFormCount":1,"_relFormDetails":[{"name":"Purchase Order Line","entity":"msdyn_purchaseorderline","formType":"Main","formId":"frm-msdyn-purchaseorderline-main"}],"_relViewCount":2,"_relViewDetails":[{"name":"Active Purchase Order Lines","entity":"msdyn_purchaseorderline","viewId":"vw-msdyn-purchaseorderline-active"},{"name":"All Purchase Order Lines","entity":"msdyn_purchaseorderline","viewId":"vw-msdyn-purchaseorderline-all"}],"_relOptionSetCount":0,"_relPluginStepCount":0,"_relPluginStepDetails":[],"_relApps":[],"_colTotal":null,"_colCustom":null,"_colOOB":null,"_columns":[{"type":"string","displayName":"PO Number","logicalName":"msdyn_purchaseordernumber"},{"type":"integer","displayName":"Line Number","logicalName":"msdyn_linenumber"},{"type":"string","displayName":"Item Number","logicalName":"msdyn_itemnumber"},{"type":"decimal","displayName":"Ordered Qty","logicalName":"msdyn_orderedpurchasequantity"},{"type":"datetime","displayName":"Requested Delivery Date","logicalName":"msdyn_requesteddeliverydate"},{"type":"money","displayName":"Line Amount","logicalName":"msdyn_lineamount"},{"type":"string","displayName":"Receiving Warehouse","logicalName":"msdyn_receivingwarehouseid"}],"_entitySettings":null,"_relSolutionFootprint":["msdyn_SupplyChain"]},"metadata":{"type":"entities","id":"msdyn_purchaseorderline"}}